Pytomatas/__init__.py
Pytomatas/dfa.py
Pytomatas/nfa.py
Pytomatas/pda.py
Pytomatas/tm.py
Pytomatas-1.1.4.dist-info/LICENSE
Pytomatas-1.1.4.dist-info/METADATA
Pytomatas-1.1.4.dist-info/WHEEL
Pytomatas-1.1.4.dist-info/top_level.txt
Pytomatas-1.1.4.dist-info/RECORD
