Metadata-Version: 2.1
Name: Pytomatas
Version: 1.1.4
Summary: Simulates Automatons Acceptors DFA, NFA, PDA and Turing Machines
Home-page: https://github.com/arhcoder/Pytomatas
Author: arhcoder
Author-email: arhcoder@gmail.com
License: MIT License
Project-URL: Bug Tracker, https://github.com/arhcoder/Pytomatas/issues
Project-URL: Author, https://github.com/arhcoder
Project-URL: Source, https://github.com/arhcoder/Pytomatas
Project-URL: Contribution, https://github.com/arhcoder/Pytomatas/pulls
Keywords: Automata,Automaton,Turing Machine,Simulation,DFA,NFA,PDA,TM,Python
Platform: UNKNOWN
Classifier: Programming Language :: Python :: 3
Classifier: License :: OSI Approved :: MIT License
Classifier: Operating System :: OS Independent
Requires-Python: >=3.6
License-File: LICENSE
